_stemdescriptor
nion
nionswift_plugin
