Metadata-Version: 1.2
Name: nionswift-segmentation
Version: 0.0.3
Summary: Description.
Home-page: https://github.com/NingWang1990/segmentation_nionswift_plugin
Author: Ning wang
Author-email: nwang@mpie.de
License: GPLv3
Platform: UNKNOWN
Requires-Python: ~=3.5
